apricity_labs.py
apricity/__init__.py
apricity/modules/__init__.py
apricity/modules/Token/Token.py
apricity/modules/Token/__init__.py
apricity/modules/Validator/__init__.py
apricity/modules/Validator/cerberus.py
apricity/objects/__init__.py
apricity/objects/Log/__init__.py
apricity/objects/Result/__init__.py
apricity/objects/Route/__init__.py
apricity/objects/Token/Token.py
apricity/objects/Token/__init__.py
apricity/objects/Token/utils.py
apricity/objects/Validator/__init__.py
apricity/objects/Validator/cerberus.py
apricity/objects/Validator/general.py
apricity/services/__init__.py
apricity/services/account/__init__.py
apricity/services/account/register.py
apricity/services/account/routes.py
apricity/services/auth/__init__.py
apricity/services/auth/authorize.py
apricity/services/auth/routes.py
apricity/services/errors/__init__.py
apricity/services/errors/register.py
apricity/services/errors/routes.py
apricity/services/home/__init__.py
apricity/services/home/routes.py
apricity/settings/__init__.py
apricity/settings/auth.py
apricity/settings/master_control.py
apricity/settings/types.py
modules/Token/Token.py
modules/Token/__init__.py
modules/Validator/__init__.py
modules/Validator/cerberus.py
services/auth/__init__.py
services/auth/authorize.py
services/auth/routes.py
services/home/__init__.py
services/home/routes.py
settings/__init__.py
settings/auth.py
settings/master_control.py
settings/types.py
apricity_labs_colemen-0.0.8.dist-info/METADATA
apricity_labs_colemen-0.0.8.dist-info/WHEEL
apricity_labs_colemen-0.0.8.dist-info/top_level.txt
apricity_labs_colemen-0.0.8.dist-info/RECORD
