Metadata-Version: 2.1
Name: apricity-labs-colemen
Version: 0.0.8
Summary: apricity_labs_colemen
Author: Colemen Atwood
Author-email: <atwoodcolemen@gmail.com>
Keywords: python
Classifier: Development Status :: 3 - Alpha
Classifier: Intended Audience :: Education
Classifier: Programming Language :: Python :: 2
Classifier: Programming Language :: Python :: 3
Classifier: Operating System :: MacOS :: MacOS X
Classifier: Operating System :: Microsoft :: Windows
Requires-Dist: colemen-utils
Requires-Dist: flask
Requires-Dist: pyjwt
Requires-Dist: cerberus
